nicostick/__init__.py
nicostick/const.py
nicostick/controller.py
nicostick/models.py
nicostick/protocol.py
nicostick-0.1.0.dist-info/LICENSE
nicostick-0.1.0.dist-info/METADATA
nicostick-0.1.0.dist-info/WHEEL
nicostick-0.1.0.dist-info/RECORD
