Metadata-Version: 2.1
Name: nicostick
Version: 0.1.0
Summary: Python package for interfacing with the Nicolaudie Stick3-DE DMX controller over Ethernet
Home-page: https://github.com/blitzkopf/shadeorb
License: MIT
Keywords: nicolaudie,stick3,dmx,lighting,controller
Author: Yngvi Thor Sigurjonsson
Author-email: blitzkopf@gmail.com
Requires-Python: >=3.10,<3.13
Classifier: Development Status :: 2 - Pre-Alpha
Classifier: License :: OSI Approved :: MIT License
Classifier: Programming Language :: Python :: 3
Classifier: Programming Language :: Python :: 3.10
Classifier: Programming Language :: Python :: 3.11
Classifier: Programming Language :: Python :: 3.12
Classifier: Topic :: Home Automation
Requires-Dist: black (>=24.2.0,<25.0.0)
Requires-Dist: pre-commit (>=3.6.2,<4.0.0)
Requires-Dist: pytest (>=8.0.2,<9.0.0)
Requires-Dist: ruff (>=0.3.0,<0.4.0)
Project-URL: Repository, https://github.com/blitzkopf/shadeorb
